[
  {
    "id": "169ca7f0-d146-4f60-8668-5864f6aba562",
    "data": [
      {
        "text": "score dashboard link",
        "userDefined": false
      }
    ],
    "isTemplate": false,
    "count": 0,
    "lang": "en",
    "updated": 0
  },
  {
    "id": "52b02e30-69f7-4310-8c84-dcd690cc5835",
    "data": [
      {
        "text": "score link",
        "userDefined": false
      }
    ],
    "isTemplate": false,
    "count": 0,
    "lang": "en",
    "updated": 0
  },
  {
    "id": "e0bfc6bb-bf73-4a7b-bfb6-a1627fab16dd",
    "data": [
      {
        "text": "where is the dashboard?",
        "userDefined": false
      }
    ],
    "isTemplate": false,
    "count": 0,
    "lang": "en",
    "updated": 0
  },
  {
    "id": "b081ce28-5565-401c-be4a-b9e65d3dda51",
    "data": [
      {
        "text": "all the links",
        "userDefined": false
      }
    ],
    "isTemplate": false,
    "count": 0,
    "lang": "en",
    "updated": 0
  },
  {
    "id": "23e14d69-3bae-4a0e-acba-88b089265066",
    "data": [
      {
        "text": "google drive",
        "userDefined": false
      }
    ],
    "isTemplate": false,
    "count": 0,
    "lang": "en",
    "updated": 0
  },
  {
    "id": "e850b88a-98a2-43eb-93c4-917b2fdc0009",
    "data": [
      {
        "text": "google drive link",
        "userDefined": false
      }
    ],
    "isTemplate": false,
    "count": 0,
    "lang": "en",
    "updated": 0
  },
  {
    "id": "3a36327e-9c54-4b04-9218-8f7af693c2a5",
    "data": [
      {
        "text": "material links",
        "userDefined": false
      }
    ],
    "isTemplate": false,
    "count": 0,
    "lang": "en",
    "updated": 0
  },
  {
    "id": "d06ad2f7-18dc-4649-acf8-7bd2e64681ac",
    "data": [
      {
        "text": "zoom link",
        "userDefined": false
      }
    ],
    "isTemplate": false,
    "count": 0,
    "lang": "en",
    "updated": 0
  },
  {
    "id": "e0719318-05f1-481d-a251-c05a155e6af3",
    "data": [
      {
        "text": "where is the zoom link?",
        "userDefined": false
      }
    ],
    "isTemplate": false,
    "count": 0,
    "lang": "en",
    "updated": 0
  },
  {
    "id": "c663b918-a499-4a90-b6f6-d8d42182639e",
    "data": [
      {
        "text": "give me links",
        "userDefined": false
      }
    ],
    "isTemplate": false,
    "count": 0,
    "lang": "en",
    "updated": 0
  },
  {
    "id": "4807d9bd-d7e6-4819-8702-28f3c0dda6be",
    "data": [
      {
        "text": "where is the link?",
        "userDefined": false
      }
    ],
    "isTemplate": false,
    "count": 0,
    "lang": "en",
    "updated": 0
  },
  {
    "id": "97bdb2d6-89d5-42da-937c-87b3d6f45855",
    "data": [
      {
        "text": "important information",
        "userDefined": false
      }
    ],
    "isTemplate": false,
    "count": 0,
    "lang": "en",
    "updated": 0
  },
  {
    "id": "323461a4-61e0-4418-b131-ed6af6ac42d6",
    "data": [
      {
        "text": "important info",
        "userDefined": false
      }
    ],
    "isTemplate": false,
    "count": 0,
    "lang": "en",
    "updated": 0
  },
  {
    "id": "f06b0b37-a509-4af9-8ee2-2842a2332884",
    "data": [
      {
        "text": "helpful links",
        "userDefined": false
      }
    ],
    "isTemplate": false,
    "count": 0,
    "lang": "en",
    "updated": 0
  },
  {
    "id": "49b55db7-5899-42ad-bef7-dca1f979ba50",
    "data": [
      {
        "text": "Can you show me useful links?",
        "userDefined": false
      }
    ],
    "isTemplate": false,
    "count": 0,
    "lang": "en",
    "updated": 0
  },
  {
    "id": "cf6eff55-5fe2-4fe2-a950-9a99f00676ae",
    "data": [
      {
        "text": "Can you show me links?",
        "userDefined": false
      }
    ],
    "isTemplate": false,
    "count": 0,
    "lang": "en",
    "updated": 0
  }
]